<?xml version="1.0" encoding="utf-8"?>
<track>
    <tts_key key="LEFT_1"/>
    <tts_key key="TIGHTLY"/>
    <tts_key key="LONG"/>
    <spawn x="30" y="0"/>
    <finish x="10" y="210"/>
    <left></left>
    <point x="0" y="0"/>
    <point x="0" y="60"/>
    <point x="0" y="60"/>
    <point x="-70" y="180"/>
    <point x="-70" y="210"/>
    <right></right>
    <point x="60" y="0"/>
    <point x="60" y="60"/>
    <point x="60" y="80"/>
    <point x="-10" y="180"/>
    <point x="-10" y="210"/>
</track>
